geo_city_locator/__init__.py
geo_city_locator/nearest_city.py
geo_city_locator/photo_utils.py
geo_city_locator-0.1.1.dist-info/METADATA
geo_city_locator-0.1.1.dist-info/WHEEL
geo_city_locator-0.1.1.dist-info/entry_points.txt
geo_city_locator-0.1.1.dist-info/top_level.txt
geo_city_locator-0.1.1.dist-info/RECORD
