Metadata-Version: 2.4
Name: geo-city-locator
Version: 0.1.1
Summary: Find the nearest city to any geographic coordinates or from photo metadata
Home-page: https://github.com/yourusername/geo-city-locator
Author: GeoCityLocator Team
Author-email: GeoCityLocator Team <example@geocitylocator.org>
License: MIT
Project-URL: Homepage, https://github.com/AlexZhangji/geo-city-locator
Project-URL: Documentation, https://geocitylocator.readthedocs.io/
Project-URL: Repository, https://github.com/AlexZhangji/geo-city-locator.git
Project-URL: Bug Tracker, https://github.com/AlexZhangji/geo-city-locator/issues
Classifier: Programming Language :: Python :: 3
Classifier: Programming Language :: Python :: 3.7
Classifier: Programming Language :: Python :: 3.8
Classifier: Programming Language :: Python :: 3.9
Classifier: Programming Language :: Python :: 3.10
Classifier: License :: OSI Approved :: MIT License
Classifier: Operating System :: OS Independent
Classifier: Topic :: Utilities
Classifier: Topic :: Multimedia :: Graphics
Classifier: Topic :: Scientific/Engineering :: GIS
Requires-Python: >=3.7
Requires-Dist: requests>=2.25.0
Requires-Dist: pillow>=8.0.0
Requires-Dist: pandas>=1.0.0
Requires-Dist: numpy>=1.18.0
Requires-Dist: appdirs>=1.4.4
Provides-Extra: web
Requires-Dist: streamlit>=1.0.0; extra == "web"
Requires-Dist: folium>=0.12.0; extra == "web"
Requires-Dist: streamlit-folium>=0.6.0; extra == "web"
Provides-Extra: dev
Requires-Dist: pytest>=6.0.0; extra == "dev"
Requires-Dist: black>=22.0.0; extra == "dev"
Requires-Dist: flake8>=4.0.0; extra == "dev"
Requires-Dist: mypy>=0.900; extra == "dev"
Requires-Dist: sphinx>=4.0.0; extra == "dev"
Dynamic: author
Dynamic: home-page
Dynamic: requires-python
